{
  "_class": "shapePath",
  "booleanOperation": -1,
  "do_objectID": "296507A1-D8B2-40C6-978B-63C5E21FA45C",
  "edited": true,
  "exportOptions": {
    "_class": "exportOptions",
    "exportFormats": [
    ],
    "includedLayerIds": [
    ],
    "layerOptions": 0,
    "shouldTrim": false
  },
  "frame": {
    "_class": "rect",
    "constrainProportions": false,
    "height": 13.70699999999999,
    "width": 82.207,
    "x": 8.30609755980413,
    "y": 545.293
  },
  "isClosed": true,
  "isFixedToViewport": false,
  "isFlippedHorizontal": false,
  "isFlippedVertical": false,
  "isLocked": false,
  "isVisible": true,
  "layerListExpandedType": 0,
  "name": "Path",
  "nameIsFixed": false,
  "pointRadiusBehaviour": 1,
  "points": [
    {
      "_class": "curvePoint",
      "cornerRadius": 0,
      "curveFrom": "{0.026591409490675028, 0.26263952724885276}",
      "curveMode": 4,
      "curveTo": "{0, 0.10315896986940891}",
      "hasCurveFrom": true,
      "hasCurveTo": false,
      "point": "{0, 0.10315896986940891}"
    },
    {
      "_class": "curvePoint",
      "cornerRadius": 0,
      "curveFrom": "{0.13605897308015066, 0.63084555336689663}",
      "curveMode": 2,
      "curveTo": "{0.055445400026761626, 0.4003793682060221}",
      "hasCurveFrom": true,
      "hasCurveTo": true,
      "point": "{0.095831255245902774, 0.51586780477128691}"
    },
    {
      "_class": "curvePoint",
      "cornerRadius": 0,
      "curveFrom": "{0.40001459729706734, 0.93630991464215019}",
      "curveMode": 3,
      "curveTo": "{0.1872346637147681, 0.72247756620704928}",
      "hasCurveFrom": true,
      "hasCurveTo": true,
      "point": "{0.25823834953227742, 0.79382797110965031}"
    },
    {
      "_class": "curvePoint",
      "cornerRadius": 0,
      "curveFrom": "{1, 1}",
      "curveMode": 4,
      "curveTo": "{0.62295181675526434, 1}",
      "hasCurveFrom": false,
      "hasCurveTo": true,
      "point": "{1, 1}"
    },
    {
      "_class": "curvePoint",
      "cornerRadius": 0,
      "curveFrom": "{0.6228545014414828, 0.85408915152841602}",
      "curveMode": 4,
      "curveTo": "{1, 0.85408915152841602}",
      "hasCurveFrom": true,
      "hasCurveTo": false,
      "point": "{1, 0.85408915152841602}"
    },
    {
      "_class": "curvePoint",
      "cornerRadius": 0,
      "curveFrom": "{0.19262349921539434, 0.57992266725030706}",
      "curveMode": 3,
      "curveTo": "{0.40179060177357129, 0.79010724447363001}",
      "hasCurveFrom": true,
      "hasCurveTo": true,
      "point": "{0.26226477063996917, 0.6498869190924359}"
    },
    {
      "_class": "curvePoint",
      "cornerRadius": 0,
      "curveFrom": "{0.068960064228106896, 0.27730356752024848}",
      "curveMode": 2,
      "curveTo": "{0.143819869354191, 0.49142773765229397}",
      "hasCurveFrom": true,
      "hasCurveTo": true,
      "point": "{0.10630481589158976, 0.38411030860144368}"
    },
    {
      "_class": "curvePoint",
      "cornerRadius": 0,
      "curveFrom": "{0.017200481710803062, 0}",
      "curveMode": 4,
      "curveTo": "{0.042307832666317373, 0.15057999562267202}",
      "hasCurveFrom": false,
      "hasCurveTo": true,
      "point": "{0.017200481710803062, 0}"
    }
  ],
  "resizingConstraint": 63,
  "resizingType": 0,
  "rotation": 0,
  "shouldBreakMaskChain": false
}